README.md
setup.cfg
setup.py
django_netaxept_gateway.egg-info/PKG-INFO
django_netaxept_gateway.egg-info/SOURCES.txt
django_netaxept_gateway.egg-info/dependency_links.txt
django_netaxept_gateway.egg-info/requires.txt
django_netaxept_gateway.egg-info/top_level.txt
netaxept/__init__.py
netaxept/actions.py
netaxept/admin.py
netaxept/apps.py
netaxept/gateway.py
netaxept/models.py
netaxept/migrations/0001_initial.py
netaxept/migrations/0002_auto_20180408_1151.py
netaxept/migrations/0003_payment_authoauth_and_redirecturl.py
netaxept/migrations/__init__.py
netaxept/templates/admin/netaxept/form.html
netaxept/templates/netaxept/example/form.html
netaxept/views/__init__.py
netaxept/views/example.py